emota_loader/__init__.py
emota_loader/dataset.py
emota_loader/utils.py
emota_loader-2.0.0.dist-info/METADATA
emota_loader-2.0.0.dist-info/WHEEL
emota_loader-2.0.0.dist-info/top_level.txt
emota_loader-2.0.0.dist-info/RECORD
