Metadata-Version: 2.4
Name: emota-loader
Version: 2.0.0
Summary: Add your description here
Requires-Python: >=3.10
